SecLoad/__init__.py
SecLoad/apihandlers.py
SecLoad/enums.py
SecLoadSDK-1.0.1.dist-info/METADATA
SecLoadSDK-1.0.1.dist-info/WHEEL
SecLoadSDK-1.0.1.dist-info/top_level.txt
SecLoadSDK-1.0.1.dist-info/RECORD
