Metadata-Version: 2.1
Name: SecLoadSDK
Version: 1.0.1
Summary: SecLoad SDK package for Roblox Script Builder APIs.
Home-page: UNKNOWN
Author: equsjd
License: UNKNOWN
Keywords: roblox
Platform: UNKNOWN
Classifier: Development Status :: 3 - Alpha
Classifier: Programming Language :: Python :: 3
